setup.cfg
setup.py
BMG_Kotara.egg-info/PKG-INFO
BMG_Kotara.egg-info/SOURCES.txt
BMG_Kotara.egg-info/dependency_links.txt
BMG_Kotara.egg-info/not-zip-safe
BMG_Kotara.egg-info/requires.txt
BMG_Kotara.egg-info/top_level.txt
BMG_NFS/__init__.py
BMG_NFS/взаимодействие_с_ТГ.py
BMG_NFS/проверка_элиментов.py
BMG_NFS/работа_спайтоном.py
BMG_NFS/терминал.py
BMG_NFS/тест теория.py
BMG_NFS/тест.py