Metadata-Version: 2.1
Name: BMG-Kotara
Version: 0.4
Summary: мои инструменты
Author-email: miniindra7@gmail.com
